dripfeed.py
dripfeed/__init__.py
dripfeed/api.py
dripfeed_client-0.1.3.dist-info/LICENSE
dripfeed_client-0.1.3.dist-info/METADATA
dripfeed_client-0.1.3.dist-info/WHEEL
dripfeed_client-0.1.3.dist-info/top_level.txt
dripfeed_client-0.1.3.dist-info/RECORD
